README.txt
VERSION.txt
iway_certbot_dns_auth/__init__.py
iway_certbot_dns_auth/api.py
iway_certbot_dns_auth/dns_challenge.py
iway_certbot_dns_auth/hooks.py
iway_certbot_dns_auth/utils.py
requirements-dev.txt
requirements.txt
iway_certbot_dns_auth-0.2.1.dist-info/LICENSE
iway_certbot_dns_auth-0.2.1.dist-info/METADATA
iway_certbot_dns_auth-0.2.1.dist-info/WHEEL
iway_certbot_dns_auth-0.2.1.dist-info/entry_points.txt
iway_certbot_dns_auth-0.2.1.dist-info/RECORD
