Metadata-Version: 2.1
Name: iway-certbot-dns-auth
Version: 0.2.1
Summary: Certbot hook for DNS challenge using iWay Portal API.
Home-page: https://github.com/iwayag/iway-certbot-dns-auth
License: MIT
Author: Frank Bohnsack
Author-email: frank.bohnsack@iway.ch
Requires-Python: >=3.8,<4.0
Classifier: License :: OSI Approved :: MIT License
Classifier: Programming Language :: Python :: 3
Classifier: Programming Language :: Python :: 3.8
Classifier: Programming Language :: Python :: 3.9
Classifier: Programming Language :: Python :: 3.10
Classifier: Programming Language :: Python :: 3.11
Classifier: Programming Language :: Python :: 3.12
Requires-Dist: PyYAML (>=5.3)
Requires-Dist: requests (>=2.27.1,<3.0.0)
Project-URL: Repository, https://github.com/iwayag/iway-certbot-dns-auth
Project-URL: issues, https://github.com/iwayag/iway-certbot-dns-auth/issues
